LICENSE
README.md
setup.py
minds_cli/__about__.py
minds_cli/__init__.py
minds_cli/__main__.py
minds_cli/cli.py
minds_cli_sdk.egg-info/PKG-INFO
minds_cli_sdk.egg-info/SOURCES.txt
minds_cli_sdk.egg-info/dependency_links.txt
minds_cli_sdk.egg-info/entry_points.txt
minds_cli_sdk.egg-info/requires.txt
minds_cli_sdk.egg-info/top_level.txt
tests/test_minds_cli.py