Metadata-Version: 2.1
Name: minds-cli-sdk
Version: 1.0.3
Summary: A command-line tool for interacting with minds
Home-page: https://github.com/Better-Boy/minds-cli-sdk
Download-URL: https://pypi.org/project/minds-cli-sdk/
Author: Abhilash K R
License: Apache License, Version 2.0
Project-URL: Issues, https://github.com/Better-Boy/minds-cli-sdk/issues
Project-URL: CI, https://github.com/Better-Boy/minds-cli-sdk/actions
Project-URL: Changelog, https://github.com/Better-Boy/minds-cli-sdk/releases
Keywords: minds mindsdb ai
Requires-Python: >=3.7
License-File: LICENSE
Requires-Dist: click
Requires-Dist: minds-sdk
Provides-Extra: test
Requires-Dist: pytest; extra == "test"
Requires-Dist: pytest-mock; extra == "test"
